{"1111":{"matrix":[[{"food":1,"manufacture":1,"building":null},{"food":1,"manufacture":1,"building":null},{"food":1,"manufacture":1,"building":null},{"food":1,"manufacture":1,"building":null},{"food":1,"manufacture":1,"building":null},{"food":1,"manufacture":1,"building":null},{"food":1,"manufacture":1,"building":null},{"food":1,"manufacture":1,"building":null},{"food":1,"manufacture":1,"building":null},{"food":1,"manufacture":1,"building":null}],[{"food":1,"manufacture":1,"building":null},{"food":1,"manufacture":1,"building":null},{"food":1,"manufacture":1,"building":null},{"food":1,"manufacture":1,"building":null},{"food":1,"manufacture":1,"building":null},{"food":1,"manufacture":1,"building":null},{"food":1,"manufacture":1,"building":null},{"food":1,"manufacture":1,"building":null},{"food":1,"manufacture":1,"building":null},{"food":1,"manufacture":1,"building":null}],[{"food":1,"manufacture":1,"building":null},{"food":1,"manufacture":1,"building":null},{"food":1,"manufacture":1,"building":null},{"food":1,"manufacture":1,"building":null},{"food":1,"manufacture":1,"building":null},{"food":1,"manufacture":1,"building":null},{"food":1,"manufacture":1,"building":null},{"food":1,"manufacture":1,"building":null},{"food":1,"manufacture":1,"building":null},{"food":1,"manufacture":1,"building":null}],[{"food":1,"manufacture":1,"building":null},{"food":2,"manufacture":1,"building":"./assets/img/Farm.png"},{"food":2,"manufacture":1,"building":"./assets/img/Farm.png"},{"food":1,"manufacture":1,"building":null},{"food":1,"manufacture":1,"building":null},{"food":1,"manufacture":1,"building":null},{"food":1,"manufacture":1,"building":null},{"food":1,"manufacture":1,"building":null},{"food":1,"manufacture":1,"building":null},{"food":1,"manufacture":1,"building":null}],[{"food":1,"manufacture":1,"building":null},{"food":1,"manufacture":1,"building":null},{"food":1,"manufacture":1,"building":null},{"food":1,"manufacture":1,"building":null},{"food":1,"manufacture":1,"building":null},{"food":1,"manufacture":1,"building":null},{"food":1,"manufacture":1,"building":null},{"food":1,"manufacture":1,"building":null},{"food":1,"manufacture":1,"building":null},{"food":1,"manufacture":1,"building":null}],[{"food":1,"manufacture":1,"building":null},{"food":1,"manufacture":1,"building":null},{"food":1,"manufacture":1,"building":null},{"food":1,"manufacture":1,"building":null},{"food":1,"manufacture":1,"building":null},{"food":1,"manufacture":1,"building":null},{"food":1,"manufacture":1,"building":null},{"food":1,"manufacture":1,"building":null},{"food":1,"manufacture":1,"building":null},{"food":1,"manufacture":1,"building":null}],[{"food":1,"manufacture":1,"building":null},{"food":1,"manufacture":1,"building":null},{"food":1,"manufacture":1,"building":null},{"food":1,"manufacture":1,"building":null},{"food":1,"manufacture":1,"building":null},{"food":1,"manufacture":1,"building":null},{"food":1,"manufacture":1,"building":null},{"food":1,"manufacture":1,"building":null},{"food":1,"manufacture":1,"building":null},{"food":1,"manufacture":1,"building":null}],[{"food":1,"manufacture":1,"building":null},{"food":1,"manufacture":1,"building":null},{"food":1,"manufacture":1,"building":null},{"food":1,"manufacture":1,"building":null},{"food":1,"manufacture":1,"building":null},{"food":1,"manufacture":1,"building":null},{"food":1,"manufacture":1,"building":null},{"food":1,"manufacture":1,"building":null},{"food":1,"manufacture":1,"building":null},{"food":1,"manufacture":1,"building":null}],[{"food":1,"manufacture":1,"building":null},{"food":1,"manufacture":1,"building":null},{"food":1,"manufacture":1,"building":null},{"food":1,"manufacture":1,"building":null},{"food":1,"manufacture":1,"building":null},{"food":1,"manufacture":1,"building":null},{"food":1,"manufacture":1,"building":null},{"food":1,"manufacture":1,"building":null},{"food":1,"manufacture":1,"building":null},{"food":1,"manufacture":1,"building":null}],[{"food":1,"manufacture":1,"building":null},{"food":1,"manufacture":1,"building":null},{"food":1,"manufacture":1,"building":null},{"food":1,"manufacture":1,"building":null},{"food":1,"manufacture":1,"building":null},{"food":1,"manufacture":1,"building":null},{"food":1,"manufacture":1,"building":null},{"food":1,"manufacture":1,"building":null},{"food":1,"manufacture":1,"building":null},{"food":1,"manufacture":1,"building":null}]],"units":[{"x":1,"y":1,"img":"./assets/img/Scout.png","strength":5,"id":"1","hp":100,"basePoints":2,"move":2},{"x":2,"y":3,"img":"./assets/img/Builder.png","hp":100,"basePoints":2,"strength":25,"move":2,"type":"builder","id":"64"}],"city":[{"img":"./assets/img/civ.png","cityLevel":1,"x":1,"y":2,"hp":100,"foodLevel":27,"food":10,"manufacture":8,"id":"914","buildings":[],"processing":null}]}}